bangun_ruang/luas_limas.py
bangun_ruang/luas_prisma.py
bangun_ruang/luas_tabung.py
bangun_ruang/luaskerucut.py
bangun_ruang/rumus_kubus.py
bangun_ruang/rumusbalok.py
bangundatar/jajargenjang.py
bangundatar/persegi.py
bangundatar/persegi_panjang.py
bangundatar/trapesium copy.py
bangundatar/trapesium.py
BELAJAR_bangundatar_bangunruang-0.0.13.dist-info/LICENSE.txt
BELAJAR_bangundatar_bangunruang-0.0.13.dist-info/METADATA
BELAJAR_bangundatar_bangunruang-0.0.13.dist-info/WHEEL
BELAJAR_bangundatar_bangunruang-0.0.13.dist-info/top_level.txt
BELAJAR_bangundatar_bangunruang-0.0.13.dist-info/RECORD
